pmail/__init__.py
pmail/attachment.py
pmail/commandline.py
pmail/configuration.py
pmail/mailserver.py
pmail/message.py
pmail/recipient.py
pmail/run.py
pmail/screen.py
pmail/sender.py
pmail/text.py
pmail-1.14.dist-info/METADATA
pmail-1.14.dist-info/RECORD
pmail-1.14.dist-info/WHEEL
pmail-1.14.dist-info/entry_points.txt
pmail-1.14.dist-info/top_level.txt
