Metadata-Version: 2.1
Name: pmail
Version: 1.14
Summary: Command-line e-mail sender
Home-page: https://bitbucket.org/tomaszwaraksa/pmail
Author: Tomasz Waraksa
Author-email: tomasz@waraksa.net
License: MIT
Download-URL: https://bitbucket.org/tomaszwaraksa/pmail/get/abd3be1798d3.zip
Keywords: mail client e-mail email send
Platform: UNKNOWN
Classifier: Development Status :: 4 - Beta
Classifier: Intended Audience :: End Users/Desktop
Classifier: Topic :: Communications :: Email
Classifier: Topic :: Utilities
Classifier: Environment :: Console
Classifier: License :: OSI Approved :: MIT License
Classifier: Programming Language :: Python :: 3.5
Classifier: Natural Language :: English
Classifier: Operating System :: OS Independent
Requires-Python: >=3.5
Requires-Dist: keyring
